nomad_plugin_tests/__init__.py
nomad_plugin_tests/cli.py
nomad_plugin_tests/config.py
nomad_plugin_tests/errors.py
nomad_plugin_tests/git.py
nomad_plugin_tests/package_tester.py
nomad_plugin_tests/parsing.py
nomad_plugin_tests/process.py
nomad_plugin_tests/py.typed
nomad_plugin_tests-0.2.3.dist-info/METADATA
nomad_plugin_tests-0.2.3.dist-info/WHEEL
nomad_plugin_tests-0.2.3.dist-info/entry_points.txt
nomad_plugin_tests-0.2.3.dist-info/RECORD
