Metadata-Version: 2.4
Name: nomad-plugin-tests
Version: 0.2.3
Summary: Run NOMAD plugin tests
Project-URL: Homepage, https://github.com/FAIRmat-NFDI/nomad-plugin-tests
Author-email: Ahmed Ilyas <ahmed.n.ilyas@gmail.com>
Requires-Python: >=3.10
Requires-Dist: click
Requires-Dist: tomli; python_version < '3.11'
